xia_agent_flask/__init__.py
xia_agent_flask/api.cpython-310-darwin.so
xia_agent_flask-0.0.10.dist-info/LICENSE.txt
xia_agent_flask-0.0.10.dist-info/METADATA
xia_agent_flask-0.0.10.dist-info/WHEEL
xia_agent_flask-0.0.10.dist-info/top_level.txt
xia_agent_flask-0.0.10.dist-info/RECORD
