Metadata-Version: 2.1
Name: xia-agent-flask
Version: 0.0.10
Home-page: https://develop.x-i-a.com/docs/xia-agent-flask/0.0.10/index.html
Author: X-I-A
Author-email: admin@x-i-a.com
Requires-Python: >=3.9
License-File: LICENSE.txt
Requires-Dist: Flask
Requires-Dist: xia-engine
Requires-Dist: xia-models
Requires-Dist: xia-logger
Requires-Dist: xia-agent
